<document>
<token id="1"> कैलाश </token>
<token id="2"> नाथ </token>

<token id="3"> चंडीगढ़ </token>
<token id="4"> : </token>
<token id="5"> दो </token>
<token id="6"> दिन </token>
<token id="7"> से </token>
<token id="8"> सदन </token>
<token id="9"> में </token>
<token id="10"> शांत </token>
<token id="11"> बैठी </token>
<token id="12"> कांग्रेस </token>
<token id="13"> ने </token>
<token id="14"> शीतकालीन </token>
<token id="15"> सत्र </token>
<token id="16"> के </token>
<token id="17"> अंतिम </token>
<token id="18"> क्षण </token>
<token id="19"> में </token>
<token id="20"> लोक </token>
<token id="21"> इंसाफ </token>
<token id="22"> पार्टी </token>
<token id="23"> के </token>
<token id="24"> बैंस </token>
<token id="25"> बंधुओं </token>
<token id="26"> सिमरजीत </token>
<token id="27"> सिंह </token>
<token id="28"> बैंस </token>
<token id="29"> व </token>
<token id="30"> बलविंदर </token>
<token id="31"> सिंह </token>
<token id="32"> बैंस </token>
<token id="33"> के </token>
<token id="34"> खिलाफ </token>
<token id="35"> निंदा </token>
<token id="36"> प्रस्ताव </token>
<token id="37"> पेश </token>
<token id="38"> कर </token>
<token id="39"> सबको </token>
<token id="40"> हैरान </token>
<token id="41"> कर </token>
<token id="42"> दिया </token>
<token id="43"> . </token>

<token id="44"> संसदीय </token>
<token id="45"> मामलों </token>
<token id="46"> के </token>
<token id="47"> मंत्री </token>
<token id="48"> ब्रह्म </token>
<token id="49"> मोहिंदरा </token>
<token id="50"> ने </token>
<token id="51"> बैंस </token>
<token id="52"> बंधुओं </token>
<token id="53"> की </token>
<token id="54"> ओर </token>
<token id="55"> से </token>
<token id="56"> 35 </token>
<token id="57"> लाख </token>
<token id="58"> रुपये </token>
<token id="59"> की </token>
<token id="60"> डील </token>
<token id="61"> की </token>
<token id="62"> ऑडियो </token>
<token id="63"> सीडी </token>
<token id="64"> जारी </token>
<token id="65"> करने </token>
<token id="66"> को </token>
<token id="67"> लेकर </token>
<token id="68"> हाईकोर्ट </token>
<token id="69"> के </token>
<token id="70"> चीफ </token>
<token id="71"> जस्टिस </token>
<token id="72"> से </token>
<token id="73"> अपील </token>
<token id="74"> की </token>
<token id="75"> है </token>
<token id="76"> कि </token>
<token id="77"> इस </token>
<token id="78"> मामले </token>
<token id="79"> में </token>
<token id="80"> स्वत </token>
<token id="81"> : </token>
<token id="82"> संज्ञान </token>
<token id="83"> लिया </token>
<token id="84"> जाए </token>
<token id="85"> . </token>

<token id="86"> प्रस्ताव </token>
<token id="87"> सदन </token>
<token id="88"> में </token>
<token id="89"> आते </token>
<token id="90"> ही </token>
<token id="91"> नेता </token>
<token id="92"> प्रतिपक्ष </token>
<token id="93"> सुखपाल </token>
<token id="94"> खैहरा </token>
<token id="95"> ने </token>
<token id="96"> कहा </token>

<token id="97"> ` </token>
<token id="98"> सरकार </token>
<token id="99"> उनके </token>
<token id="100"> खिलाफ </token>
<token id="101"> साजिश </token>
<token id="102"> रच </token>
<token id="103"> रही </token>
<token id="104"> है </token>
<token id="105"> . </token>

<token id="106"> संसदीय </token>
<token id="107"> मामले </token>
<token id="108"> के </token>
<token id="109"> मंत्री </token>
<token id="110"> को </token>
<token id="111"> विधायकों </token>
<token id="112"> के </token>
<token id="113"> हितों </token>
<token id="114"> की </token>
<token id="115"> रक्षा </token>
<token id="116"> करनी </token>
<token id="117"> चाहिए </token>

<token id="118"> लेकिन </token>
<token id="119"> मंत्री </token>
<token id="120"> मेरे </token>
<token id="121"> खिलाफ </token>
<token id="122"> साजिश </token>
<token id="123"> रच </token>
<token id="124"> रहे </token>
<token id="125"> हैं </token>
<token id="126"> . </token>

<token id="127"> सरकार </token>
<token id="128"> इस </token>
<token id="129"> मामले </token>
<token id="130"> की </token>
<token id="131"> सीबीआइ </token>
<token id="132"> जांच </token>
<token id="133"> करवा </token>
<token id="134"> ले </token>
<token id="135"> . </token>

<token id="136"> मैं </token>
<token id="137"> खुद </token>
<token id="138"> चीफ </token>
<token id="139"> जस्टिस </token>
<token id="140"> से </token>
<token id="141"> मिला </token>
<token id="142"> हूं </token>
<token id="143"> . </token>

<token id="144"> उन्होंने </token>
<token id="145"> मुझे </token>
<token id="146"> भरोसा </token>
<token id="147"> दिया </token>
<token id="148"> है </token>
<token id="149"> कि </token>
<token id="150"> वह </token>
<token id="151"> नाइंसाफी </token>
<token id="152"> नहीं </token>
<token id="153"> होने </token>
<token id="154"> देंगे </token>
<token id="155"> . </token>

<token id="156"> अगर </token>
<token id="157"> मैं </token>
<token id="158"> दोषी </token>
<token id="159"> हूं </token>
<token id="160"> तो </token>
<token id="161"> मुझे </token>
<token id="162"> फांसी </token>
<token id="163"> पर </token>
<token id="164"> टांग </token>
<token id="165"> दो </token>
<token id="166"> या </token>
<token id="167"> गोली </token>
<token id="168"> मार </token>
<token id="169"> दो </token>
<token id="170"> . </token>

<token id="171"> ' </token>
<token id="172"> खैहरा </token>
<token id="173"> ने </token>
<token id="174"> कहा </token>

<token id="175"> ' </token>
<token id="176"> न </token>
<token id="177"> तो </token>
<token id="178"> मैंने </token>
<token id="179"> और </token>
<token id="180"> न </token>
<token id="181"> ही </token>
<token id="182"> बैंस </token>
<token id="183"> बंधुओं </token>
<token id="184"> ने </token>
<token id="185"> कभी </token>
<token id="186"> यह </token>
<token id="187"> कहा </token>
<token id="188"> कि </token>
<token id="189"> उन्हें </token>
<token id="190"> न्यायालय </token>
<token id="191"> पर </token>
<token id="192"> भरोसा </token>
<token id="193"> नहीं </token>
<token id="194"> है </token>
<token id="195"> . </token>

<token id="196"> इसके </token>
<token id="197"> बावजूद </token>
<token id="198"> यह </token>
<token id="199"> प्रस्ताव </token>
<token id="200"> लाया </token>
<token id="201"> जा </token>
<token id="202"> रहा </token>
<token id="203"> है </token>
<token id="204"> . </token>

<token id="205"> वहीं </token>

<token id="206"> ब्रह्म </token>
<token id="207"> मोहिंदरा </token>
<token id="208"> ने </token>
<token id="209"> प्रस्ताव </token>
<token id="210"> का </token>
<token id="211"> समर्थन </token>
<token id="212"> करते </token>
<token id="213"> हुए </token>
<token id="214"> कहा </token>
<token id="215"> ` </token>
<token id="216"> प्रस्ताव </token>
<token id="217"> में </token>
<token id="218"> कोई </token>
<token id="219"> गलत </token>
<token id="220"> बात </token>
<token id="221"> नहीं </token>
<token id="222"> लिखी </token>
<token id="223"> गई </token>
<token id="224"> है </token>
<token id="225"> . </token>

<token id="226"> खैहरा </token>
<token id="227"> सीबीआइ </token>
<token id="228"> जांच </token>
<token id="229"> की </token>
<token id="230"> मांग </token>
<token id="231"> कर </token>
<token id="232"> रहे </token>
<token id="233"> थे </token>
<token id="234"> . </token>

<token id="235"> न्यायिक </token>
<token id="236"> जांच </token>
<token id="237"> हो </token>
<token id="238"> जाएगी </token>
<token id="239"> . </token>

<token id="240"> तो </token>
<token id="241"> इससे </token>
<token id="242"> बेहतर </token>
<token id="243"> क्या </token>
<token id="244"> होगा </token>
<token id="245"> . </token>

<token id="246"> ' </token>
<token id="247"> इसके </token>
<token id="248"> बाद </token>
<token id="249"> आप </token>
<token id="250"> विधायकों </token>
<token id="251"> व </token>
<token id="252"> बैंस </token>
<token id="253"> बंधुओं </token>
<token id="254"> ने </token>
<token id="255"> प्रस्ताव </token>
<token id="256"> के </token>
<token id="257"> खिलाफ </token>
<token id="258"> नारेबाजी </token>
<token id="259"> शुरू </token>
<token id="260"> कर </token>
<token id="261"> दी </token>
<token id="262"> . </token>

<token id="263"> अकाली </token>
<token id="264"> दल </token>
<token id="265"> के </token>
<token id="266"> विधायक </token>
<token id="267"> शांत </token>
<token id="268"> बैठे </token>
<token id="269"> रहे </token>
<token id="270"> . </token>

<token id="271"> जबकि </token>
<token id="272"> आप </token>
<token id="273"> विधायक </token>
<token id="274"> सदन </token>
<token id="275"> से </token>
<token id="276"> वॉकआउट </token>
<token id="277"> कर </token>
<token id="278"> गए </token>
<token id="279"> और </token>
<token id="280"> हंगामे </token>
<token id="281"> के </token>
<token id="282"> बीच </token>
<token id="283"> प्रस्ताव </token>
<token id="284"> पारित </token>
<token id="285"> हुआ </token>
<token id="286"> . </token>

<token id="287"> निंदा </token>
<token id="288"> प्रस्ताव </token>
<token id="289"> पर </token>
<token id="290"> सरकार </token>
<token id="291"> ने </token>
<token id="292"> इतनी </token>
<token id="293"> गोपनीयता </token>
<token id="294"> रखी </token>
<token id="295"> कि </token>
<token id="296"> इसकी </token>
<token id="297"> जानकारी </token>
<token id="298"> स्पीकर </token>
<token id="299"> तक </token>
<token id="300"> को </token>
<token id="301"> नहीं </token>
<token id="302"> हो </token>
<token id="303"> पाई </token>
<token id="304"> . </token>

<token id="305"> जब </token>
<token id="306"> ब्रह्म </token>
<token id="307"> मोहिंदरा </token>
<token id="308"> खड़े </token>
<token id="309"> हुए </token>

<token id="310"> तो </token>
<token id="311"> स्पीकर </token>
<token id="312"> ने </token>
<token id="313"> उन्हें </token>
<token id="314"> अनाज </token>
<token id="315"> खरीद </token>
<token id="316"> पर </token>
<token id="317"> सरकारी </token>
<token id="318"> प्रस्ताव </token>
<token id="319"> पढ़ने </token>
<token id="320"> को </token>
<token id="321"> कहा </token>

<token id="322"> लेकिन </token>
<token id="323"> मंत्री </token>
<token id="324"> ने </token>
<token id="325"> कहा </token>
<token id="326"> कि </token>
<token id="327"> वह </token>
<token id="328"> एक </token>
<token id="329"> और </token>
<token id="330"> प्रस्ताव </token>
<token id="331"> लेकर </token>
<token id="332"> आ </token>
<token id="333"> रहे </token>
<token id="334"> हैं </token>
<token id="335"> . </token>

<token id="336"> सदन </token>
<token id="337"> की </token>
<token id="338"> कार्यवाही </token>
<token id="339"> खत्म </token>
<token id="340"> होने </token>
<token id="341"> के </token>
<token id="342"> बाद </token>
<token id="343"> कांग्रेस </token>
<token id="344"> के </token>
<token id="345"> ही </token>
<token id="346"> कई </token>
<token id="347"> विधायक </token>
<token id="348"> निंदा </token>
<token id="349"> प्रस्ताव </token>
<token id="350"> के </token>
<token id="351"> फैसले </token>
<token id="352"> पर </token>
<token id="353"> सहमत </token>
<token id="354"> नहीं </token>
<token id="355"> दिखे </token>
<token id="356"> . </token>

<token id="357"> 27 </token>
<token id="358"> नवंबर </token>
<token id="359"> को </token>
<token id="360"> बैंस </token>
<token id="361"> बंधुओं </token>
<token id="362"> ने </token>
<token id="363"> एक </token>
<token id="364"> ऑडियो </token>
<token id="365"> रिकॉर्डिंग </token>
<token id="366"> जारी </token>
<token id="367"> करते </token>
<token id="368"> हुए </token>
<token id="369"> दावा </token>
<token id="370"> किया </token>
<token id="371"> था </token>
<token id="372"> कि </token>
<token id="373"> आप </token>
<token id="374"> विधायक </token>
<token id="375"> सुखपाल </token>
<token id="376"> खैहरा </token>
<token id="377"> को </token>
<token id="378"> ड्रग्स </token>
<token id="379"> मामले </token>
<token id="380"> में </token>
<token id="381"> फंसाने </token>
<token id="382"> के </token>
<token id="383"> लिए </token>
<token id="384"> 35 </token>
<token id="385"> लाख </token>
<token id="386"> रुपये </token>
<token id="387"> में </token>
<token id="388"> डील </token>
<token id="389"> की </token>
<token id="390"> गई </token>
<token id="391"> है </token>
<token id="392"> . </token>

<token id="393"> रिकॉर्डिग </token>
<token id="394"> में </token>
<token id="395"> बर्खास्त </token>
<token id="396"> पीसीएस </token>
<token id="397"> अधिकारी </token>
<token id="398"> टीके </token>
<token id="399"> गोयल </token>
<token id="400"> व </token>
<token id="401"> पूर्व </token>
<token id="402"> अकाली-भाजपा </token>
<token id="403"> सरकार </token>
<token id="404"> में </token>
<token id="405"> एडिशनल </token>
<token id="406"> एडवोकेट </token>
<token id="407"> जनरल </token>
<token id="408"> अमित </token>
<token id="409"> चौधरी </token>
<token id="410"> के </token>
<token id="411"> बीच </token>
<token id="412"> खैहरा </token>
<token id="413"> को </token>
<token id="414"> अदालत </token>
<token id="415"> से </token>
<token id="416"> राहत </token>
<token id="417"> न </token>
<token id="418"> मिलने </token>
<token id="419"> की </token>
<token id="420"> बातचीत </token>
<token id="421"> का </token>
<token id="422"> दावा </token>
<token id="423"> किया </token>
<token id="424"> गया </token>
<token id="425"> था </token>
<token id="426"> . </token>
<EVENT id="e1" class="OCC " tokens="37,38" AnnConf="High"/>
<EVENT id="e10" class="OCC " tokens="122,123,124,125" AnnConf="High"/>
<EVENT id="e11" class="OCC " tokens="132,133,134" AnnConf="High"/>
<EVENT id="e12" class="OCC " tokens="141,142" AnnConf="High"/>
<EVENT id="e13" class="OCC " tokens="146,147,148" AnnConf="High"/>
<EVENT id="e14" class="OCC " tokens="151,152,153,154" AnnConf="High"/>
<EVENT id="e15" class="OCC " tokens="164,165" AnnConf="High"/>
<EVENT id="e16" class="OCC " tokens="167,168,169" AnnConf="High"/>
<EVENT id="e17" class="REP " tokens="174" AnnConf="High"/>
<EVENT id="e18" class="REP " tokens="187" AnnConf="High"/>
<EVENT id="e19" class="OCC " tokens="192,193,194" AnnConf="High"/>
<EVENT id="e2" class="OCC " tokens="40,41,42" AnnConf="High"/>
<EVENT id="e20" class="OCC " tokens="199,200,201,202,203" AnnConf="High"/>
<EVENT id="e21" class="OCC " tokens="211,212,213" AnnConf="High"/>
<EVENT id="e22" class="REP " tokens="214" AnnConf="High"/>
<EVENT id="e23" class="OCC " tokens="221,222,223,224" AnnConf="High"/>
<EVENT id="e24" class="OCC " tokens="228" AnnConf="High"/>
<EVENT id="e25" class="OCC " tokens="230,231,232,233" AnnConf="High"/>
<EVENT id="e26" class="OCC " tokens="236,237,238" AnnConf="High"/>
<EVENT id="e27" class="OCC " tokens="258" AnnConf="High"/>
<EVENT id="e28" class="ASP " tokens="259,260,261" AnnConf="High"/>
<EVENT id="e29" class="OCC " tokens="268,269" AnnConf="High"/>
<EVENT id="e3" class="OCC " tokens="64,65" AnnConf="High"/>
<EVENT id="e30" class="OCC " tokens="276,277,278" AnnConf="High"/>
<EVENT id="e31" class="OCC " tokens="284,285" AnnConf="High"/>
<EVENT id="e32" class="OCC " tokens="293,294" AnnConf="High"/>
<EVENT id="e33" class="OCC " tokens="297,301,302,303" AnnConf="High"/>
<EVENT id="e34" class="OCC " tokens="308,309" AnnConf="High"/>
<EVENT id="e35" class="OCC " tokens="314,315" AnnConf="High"/>
<EVENT id="e36" class="OCC " tokens="319" AnnConf="High"/>
<EVENT id="e37" class="REP " tokens="321" AnnConf="High"/>
<EVENT id="e38" class="REP " tokens="325" AnnConf="High"/>
<EVENT id="e39" class="OCC " tokens="332,333,334" AnnConf="High"/>
<EVENT id="e4" class="OCC " tokens="73,74,75" AnnConf="High"/>
<EVENT id="e40" class="OCC " tokens="338" AnnConf="High"/>
<EVENT id="e41" class="ASP " tokens="339,340" AnnConf="High"/>
<EVENT id="e42" class="OCC " tokens="353,354,355" AnnConf="High"/>
<EVENT id="e43" class="OCC " tokens="366,367,368" AnnConf="High"/>
<EVENT id="e44" class="OCC " tokens="369,370,371" AnnConf="High"/>
<EVENT id="e45" class="OCC " tokens="378,379" AnnConf="High"/>
<EVENT id="e46" class="OCC " tokens="381" AnnConf="High"/>
<EVENT id="e47" class="OCC " tokens="388,389,390,391" AnnConf="High"/>
<EVENT id="e48" class="OCC " tokens="416,417,418" AnnConf="High"/>
<EVENT id="e49" class="OCC " tokens="422,423,424,425" AnnConf="High"/>
<EVENT id="e5" class="OCC " tokens="82,83,84" AnnConf="High"/>
<EVENT id="e6" class="OCC " tokens="89" AnnConf="High"/>
<EVENT id="e7" class="REP " tokens="96" AnnConf="High"/>
<EVENT id="e8" class="OCC " tokens="101,102,103,104" AnnConf="High"/>
<EVENT id="e9" class="OCC " tokens="115,116,117" AnnConf="High"/>
<STATE id="s1" class="DESC" tokens="10,11" AnnConf="High"/>
<STATE id="s2" class="DECL" tokens="159" AnnConf="High"/>
<STATE id="s3" class="DECL" tokens="244" AnnConf="High"/>
<TIMEX id="t1" class="DUR" tokens="5,6" AnnConf="High"/>
<TIMEX id="t2" class="TIME" tokens="17,18" AnnConf="High"/>
<TIMEX id="t3" class="DATE" tokens="357,358" AnnConf="High"/>
<ALINK f_id="e28" s_id="e27" type="INITIATION" AnnConf="High"/>
<ALINK f_id="e41" s_id="e40" type="CULMINATION" AnnConf="High"/>
<TLINK f_id="e1" s_id="e2" class="before" AnnConf="Low"/>
<TLINK f_id="e6" s_id="e7" class="before" AnnConf="High"/>
<TLINK f_id="e12" s_id="e13" class="before" AnnConf="High"/>
<TLINK f_id="e22" s_id="e27" class="before" AnnConf="High"/>
<TLINK f_id="e27" s_id="e29" class="overlap" AnnConf="High"/>
<TLINK f_id="e30" s_id="e31" class="before" AnnConf="High"/>
<TLINK f_id="e34" s_id="e37" class="before" AnnConf="High"/>
<TLINK f_id="e37" s_id="e38" class="before" AnnConf="High"/>
<TLINK f_id="e40" s_id="e42" class="before" AnnConf="High"/>
<TLINK f_id="e43" s_id="e44" class="overlap" AnnConf="Low"/>
<SLINK f_id="e1" s_id="e2" AnnConf="High"/>
<SLINK f_id="e3" s_id="e4" AnnConf="Medium"/>
<SLINK f_id="e3" s_id="e5" AnnConf="High"/>
<SLINK f_id="e6" s_id="e7" AnnConf="High"/>
<SLINK f_id="e6" s_id="e8" AnnConf="High"/>
<SLINK f_id="e9" s_id="e10" AnnConf="High"/>
<SLINK f_id="e13" s_id="e14" AnnConf="Medium"/>
<SLINK f_id="e15" s_id="e16" AnnConf="High"/>
<SLINK f_id="e18" s_id="e19" AnnConf="Low"/>
<SLINK f_id="e21" s_id="e22" AnnConf="Low"/>
<SLINK f_id="e21" s_id="e23" AnnConf="High"/>
<SLINK f_id="e24" s_id="e25" AnnConf="High"/>
<SLINK f_id="e27" s_id="e28" AnnConf="High"/>
<SLINK f_id="e30" s_id="e31" AnnConf="High"/>
<SLINK f_id="e32" s_id="e33" AnnConf="High"/>
<SLINK f_id="e34" s_id="e35" AnnConf="High"/>
<SLINK f_id="e36" s_id="e37" AnnConf="High"/>
<SLINK f_id="e40" s_id="e41" AnnConf="High"/>
<SLINK f_id="e43" s_id="e44" AnnConf="High"/>
<SLINK f_id="e44" s_id="e45" AnnConf="High"/>
<SLINK f_id="e48" s_id="e49" AnnConf="Low"/>
</document>