<document>
<token id="1"> ( </token>
<token id="2"> भोजपुर </token>
<token id="3"> ) </token>
<token id="4"> : </token>
<token id="5"> प्रखंड </token>
<token id="6"> के </token>
<token id="7"> कमरियांव </token>
<token id="8"> गांव </token>
<token id="9"> में </token>
<token id="10"> एक </token>
<token id="11"> ठग </token>
<token id="12"> ने </token>
<token id="13"> इंदिरा </token>
<token id="14"> आवास </token>
<token id="15"> की </token>
<token id="16"> दूसरी </token>
<token id="17"> किस्त </token>
<token id="18"> तथा </token>
<token id="19"> नया </token>
<token id="20"> इंदिरा </token>
<token id="21"> आवास </token>
<token id="22"> दिलाने </token>
<token id="23"> के </token>
<token id="24"> नाम </token>
<token id="25"> पर </token>
<token id="26"> एक </token>
<token id="27"> व्यक्ति </token>
<token id="28"> से </token>
<token id="29"> 1900 </token>
<token id="30"> रुपये </token>
<token id="31"> का </token>
<token id="32"> चूना </token>
<token id="33"> लगाकर </token>
<token id="34"> चंपत </token>
<token id="35"> हो </token>
<token id="36"> गया </token>
<token id="37"> . </token>
<token id="38"> ठगी </token>
<token id="39"> का </token>
<token id="40"> शिकार </token>
<token id="41"> हुए </token>
<token id="42"> राजेन्द्र </token>
<token id="43"> यादव </token>
<token id="44"> ने </token>
<token id="45"> बीडीओ </token>
<token id="46"> को </token>
<token id="47"> उक्त </token>
<token id="48"> आशय </token>
<token id="49"> की </token>
<token id="50"> लिखित </token>
<token id="51"> सूचना </token>
<token id="52"> देते </token>
<token id="53"> हुए </token>
<token id="54"> जांच </token>
<token id="55"> और </token>
<token id="56"> कार्रवाई </token>
<token id="57"> की </token>
<token id="58"> गुहार </token>
<token id="59"> लगाई </token>
<token id="60"> है </token>
<token id="61"> . </token>
<token id="62"> कमरियांव </token>
<token id="63"> निवासी </token>
<token id="64"> राजेन्द्र </token>
<token id="65"> यादव </token>
<token id="66"> ने </token>
<token id="67"> बताया </token>
<token id="68"> कि </token>
<token id="69"> गत </token>
<token id="70"> बुधवार </token>
<token id="71"> को </token>
<token id="72"> एक </token>
<token id="73"> व्यक्ति </token>
<token id="74"> जो </token>
<token id="75"> खुद </token>
<token id="76"> को </token>
<token id="77"> बिहिया </token>
<token id="78"> ब्लॉक </token>
<token id="79"> का </token>
<token id="80"> स्टॉफ </token>
<token id="81"> बता </token>
<token id="82"> रहा </token>
<token id="83"> था </token>
<token id="84"> उनके </token>
<token id="85"> घर </token>
<token id="86"> पहुंचा </token>
<token id="87"> . </token>
<token id="88"> उसके </token>
<token id="89"> पास </token>
<token id="90"> इंदिरा </token>
<token id="91"> आवास </token>
<token id="92"> के </token>
<token id="93"> लाभार्थियों </token>
<token id="94"> की </token>
<token id="95"> पूरी </token>
<token id="96"> लिस्ट </token>
<token id="97"> थी </token>
<token id="98"> . </token>
<token id="99"> सूची </token>
<token id="100"> दिखाते </token>
<token id="101"> हुए </token>
<token id="102"> उसने </token>
<token id="103"> कहा </token>
<token id="104"> कि </token>
<token id="105"> मेरे </token>
<token id="106"> पिता </token>
<token id="107"> महेंद्र </token>
<token id="108"> प्रसाद </token>
<token id="109"> के </token>
<token id="110"> नाम </token>
<token id="111"> जो </token>
<token id="112"> इंदिरा </token>
<token id="113"> आवास </token>
<token id="114"> पास </token>
<token id="115"> है </token>
<token id="116"> उसकी </token>
<token id="117"> दूसरी </token>
<token id="118"> किस्त </token>
<token id="119"> निकालना </token>
<token id="120"> है </token>
<token id="121"> तथा </token>
<token id="122"> पैसा </token>
<token id="123"> खर्च </token>
<token id="124"> करोगे </token>
<token id="125"> तो </token>
<token id="126"> तुम्हारा </token>
<token id="127"> भी </token>
<token id="128"> आवास </token>
<token id="129"> पास </token>
<token id="130"> करा </token>
<token id="131"> दूंगा </token>
<token id="132"> . </token>
<token id="133"> दोनों </token>
<token id="134"> मिलाकर </token>
<token id="135"> 6000 </token>
<token id="136"> रुपये </token>
<token id="137"> दो </token>
<token id="138"> . </token>
<token id="139"> ठग </token>
<token id="140"> ने </token>
<token id="141"> आगे </token>
<token id="142"> कहा </token>
<token id="143"> कि </token>
<token id="144"> तुम्हारे </token>
<token id="145"> पंचायत </token>
<token id="146"> में </token>
<token id="147"> पैसा </token>
<token id="148"> खर्च </token>
<token id="149"> करने </token>
<token id="150"> पर </token>
<token id="151"> दूसरे </token>
<token id="152"> का </token>
<token id="153"> नाम </token>
<token id="154"> काटकर </token>
<token id="155"> दूसरे </token>
<token id="156"> को </token>
<token id="157"> इंदिरा </token>
<token id="158"> आवास </token>
<token id="159"> दे </token>
<token id="160"> दिया </token>
<token id="161"> गया </token>
<token id="162"> है </token>
<token id="163"> . </token>
<token id="164"> राजेन्द्र </token>
<token id="165"> यादव </token>
<token id="166"> ने </token>
<token id="167"> बताया </token>
<token id="168"> कि </token>
<token id="169"> जब </token>
<token id="170"> उसने </token>
<token id="171"> इतना </token>
<token id="172"> पैसा </token>
<token id="173"> अभी </token>
<token id="174"> नहीं </token>
<token id="175"> होने </token>
<token id="176"> की </token>
<token id="177"> बात </token>
<token id="178"> कही </token>
<token id="179"> तो </token>
<token id="180"> उसने </token>
<token id="181"> कहा </token>
<token id="182"> जो </token>
<token id="183"> है </token>
<token id="184"> वही </token>
<token id="185"> दो </token>
<token id="186"> बाद </token>
<token id="187"> में </token>
<token id="188"> समझ </token>
<token id="189"> लिया </token>
<token id="190"> जाएगा </token>
<token id="191"> . </token>
<token id="192"> इसके </token>
<token id="193"> बाद </token>
<token id="194"> राजेंद्र </token>
<token id="195"> ने </token>
<token id="196"> किसी </token>
<token id="197"> तरह </token>
<token id="198"> जोडतोड </token>
<token id="199"> कर </token>
<token id="200"> 1900 </token>
<token id="201"> रुपये </token>
<token id="202"> का </token>
<token id="203"> सिक्का </token>
<token id="204"> जुगाड </token>
<token id="205"> कर </token>
<token id="206"> ठग </token>
<token id="207"> को </token>
<token id="208"> दे </token>
<token id="209"> दिया </token>
<token id="210"> . </token>
<token id="211"> जिसके </token>
<token id="212"> बाद </token>
<token id="213"> ठग </token>
<token id="214"> ने </token>
<token id="215"> रुपये </token>
<token id="216"> को </token>
<token id="217"> गमछे </token>
<token id="218"> में </token>
<token id="219"> समेट </token>
<token id="220"> कर </token>
<token id="221"> चलते </token>
<token id="222"> बना </token>
<token id="223"> . </token>
<token id="224"> जब </token>
<token id="225"> उसे </token>
<token id="226"> ठग </token>
<token id="227"> के </token>
<token id="228"> व्यवहार </token>
<token id="229"> पर </token>
<token id="230"> शक </token>
<token id="231"> हुआ </token>
<token id="232"> तो </token>
<token id="233"> गुरुवार </token>
<token id="234"> को </token>
<token id="235"> उसने </token>
<token id="236"> ब्लॉक </token>
<token id="237"> कार्यालय </token>
<token id="238"> में </token>
<token id="239"> उसकी </token>
<token id="240"> काफी </token>
<token id="241"> तलाश </token>
<token id="242"> की </token>
<token id="243"> पर </token>
<token id="244"> उसका </token>
<token id="245"> कहीं </token>
<token id="246"> पता </token>
<token id="247"> नहीं </token>
<token id="248"> चला </token>
<token id="249"> . </token>
<token id="250"> सूत्रों </token>
<token id="251"> पर </token>
<token id="252"> भरोसा </token>
<token id="253"> करें </token>
<token id="254"> तो </token>
<token id="255"> प्रखंड </token>
<token id="256"> में </token>
<token id="257"> इंदिरा </token>
<token id="258"> बनाने </token>
<token id="259"> के </token>
<token id="260"> नाम </token>
<token id="261"> पर </token>
<token id="262"> लाभार्थियों </token>
<token id="263"> का </token>
<token id="264"> जम </token>
<token id="265"> कर </token>
<token id="266"> आर्थिक </token>
<token id="267"> शोषण </token>
<token id="268"> किया </token>
<token id="269"> जा </token>
<token id="270"> रहा </token>
<token id="271"> है </token>
<token id="272"> . </token>
<token id="273"> प्रखंड </token>
<token id="274"> में </token>
<token id="275"> क्या </token>
<token id="276"> अमीर </token>
<token id="277"> क्या </token>
<token id="278"> गरीब </token>
<token id="279"> शायद </token>
<token id="280"> हीं </token>
<token id="281"> कोई </token>
<token id="282"> है </token>
<token id="283"> जिसका </token>
<token id="284"> घर </token>
<token id="285"> अभी </token>
<token id="286"> तक </token>
<token id="287"> मिट्टी </token>
<token id="288"> का </token>
<token id="289"> बच </token>
<token id="290"> गया </token>
<token id="291"> है </token>
<token id="292"> . </token>
<token id="293"> लगभग </token>
<token id="294"> सभी </token>
<token id="295"> लोग </token>
<token id="296"> भले </token>
<token id="297"> एक </token>
<token id="298"> या </token>
<token id="299"> दो </token>
<token id="300"> कमरा </token>
<token id="301"> हीं </token>
<token id="302"> सही </token>
<token id="303"> पक्का </token>
<token id="304"> बना </token>
<token id="305"> चुके </token>
<token id="306"> हैं </token>
<token id="307"> . </token>
<token id="308"> अब </token>
<token id="309"> उनका </token>
<token id="310"> नाम </token>
<token id="311"> यदि </token>
<token id="312"> लाभार्थियों </token>
<token id="313"> की </token>
<token id="314"> लिस्ट </token>
<token id="315"> में </token>
<token id="316"> है </token>
<token id="317"> तो </token>
<token id="318"> ठगी </token>
<token id="319"> करने </token>
<token id="320"> वाले </token>
<token id="321"> उसके </token>
<token id="322"> पास </token>
<token id="323"> पहुंच </token>
<token id="324"> कर </token>
<token id="325"> पक्का </token>
<token id="326"> घर </token>
<token id="327"> होनें </token>
<token id="328"> की </token>
<token id="329"> स्थिति </token>
<token id="330"> में </token>
<token id="331"> इंदिरा </token>
<token id="332"> आवास </token>
<token id="333"> की </token>
<token id="334"> लिस्ट </token>
<token id="335"> से </token>
<token id="336"> नाम </token>
<token id="337"> हटा </token>
<token id="338"> देने </token>
<token id="339"> का </token>
<token id="340"> धौस </token>
<token id="341"> दिखाकर </token>
<token id="342"> रुपया </token>
<token id="343"> ऐंठ </token>
<token id="344"> रहे </token>
<token id="345"> हैं </token>
<token id="346"> . </token>
<EVENT id="e1" class="OCC" tokens="22" annConf="High"/>
<EVENT id="e2" class="IAC" tokens="32,33" annConf="High"/>
<EVENT id="e3" class="OCC" tokens="34,35,36" annConf="High"/>
<EVENT id="e4" class="OCC" tokens="38" annConf="High"/>
<EVENT id="e5" class="OCC" tokens="40,41" annConf="High"/>
<EVENT id="e6" class="IAC" tokens="51,52,53" annConf="High"/>
<EVENT id="e7" class="OCC" tokens="54" annConf="High"/>
<EVENT id="e8" class="OCC" tokens="56" annConf="High"/>
<EVENT id="e9" class="OCC" tokens="58,59,60" annConf="High"/>
<EVENT id="e10" class="REP" tokens="67" annConf="High"/>
<EVENT id="e11" class="OCC" tokens="81,82,83" annConf="High"/>
<EVENT id="e12" class="OCC" tokens="86" annConf="High"/>
<EVENT id="e14" class="PER" tokens="99,100,101" annConf="High"/>
<EVENT id="e15" class="REP" tokens="103" annConf="High"/>
<EVENT id="e16" class="OCC" tokens="119,120" annConf="High"/>
<EVENT id="e17" class="OCC" tokens="123,124" annConf="High"/>
<EVENT id="e18" class="OCC" tokens="129,130,131" annConf="High"/>
<EVENT id="e19" class="REP" tokens="142" annConf="High"/>
<EVENT id="e20" class="OCC" tokens="148,149" annConf="High"/>
<EVENT id="e21" class="IAC" tokens="153,154" annConf="High"/>
<EVENT id="e22" class="OCC" tokens="159,160,161,162" annConf="High"/>
<EVENT id="e23" class="REP" tokens="167" annConf="High"/>
<EVENT id="e24" class="OCC" tokens="174,175" annConf="High"/>
<EVENT id="e25" class="OCC" tokens="178" annConf="High"/>
<EVENT id="e26" class="REP" tokens="181" annConf="High"/>
<EVENT id="e27" class="OCC" tokens="185" annConf="High"/>
<EVENT id="e28" class="OCC" tokens="188,189,190" annConf="High"/>
<EVENT id="e29" class="IAC" tokens="198,199" annConf="High"/>
<EVENT id="e30" class="IAC" tokens="204,205" annConf="High"/>
<EVENT id="e31" class="OCC" tokens="208,209" annConf="High"/>
<EVENT id="e32" class="IAC" tokens="219,220" annConf="High"/>
<EVENT id="e33" class="OCC" tokens="221,222" annConf="High"/>
<EVENT id="e34" class="OCC" tokens="230,231" annConf="High"/>
<EVENT id="e35" class="OCC" tokens="241,242" annConf="High"/>
<EVENT id="e36" class="OCC" tokens="246,247,248" annConf="High"/>
<EVENT id="e37" class="OCC" tokens="252,253" annConf="High"/>
<EVENT id="e38" class="OCC" tokens="258" annConf="High"/>
<EVENT id="e39" class="OCC" tokens="264,265" annConf="High"/>
<EVENT id="e40" class="OCC" tokens="267,268,269,270,271" annConf="High"/>
<EVENT id="e41" class="OCC" tokens="289,290,291" annConf="High"/>
<EVENT id="e42" class="OCC" tokens="304,305,306" annConf="High"/>
<EVENT id="e44" class="IAC" tokens="323,324" annConf="High"/>
<EVENT id="e45" class="OCC" tokens="337,338" annConf="High"/>
<EVENT id="e46" class="PER" tokens="340,341" annConf="High"/>
<EVENT id="e47" class="OCC" tokens="343,344,345" annConf="High"/>
<STATE id="s4" class="DECL" tokens="96,97" annConf="High"/>
<STATE id="s1" class="DESC" tokens="115" annConf="High"/>
<STATE id="s2" class="DESC" tokens="183" annConf="High"/>
<STATE id="s3" class="DESC" tokens="316" annConf="High"/>
<STATE id="s5" class="DESC" tokens="318,319" annConf="High"/>
<TIMEX id="t1" tokens="69,70" annConf="High" class="DATE"/>
<TIMEX id="t2" tokens="233" annConf="High" class="SET"/>
<SLINK f_id="e10" s_id="e12" AnnConf="High"/>
<SLINK f_id="e15" s_id="e18" AnnConf="Low"/>
<SLINK f_id="e19" s_id="e22" AnnConf="High"/>
<SLINK f_id="e23" s_id="e28" AnnConf="Low"/>
<SLINK f_id="e26" s_id="e28" AnnConf="High"/>
<TLINK f_id="e2" s_id="e3" class="before" AnnConf="Medium"/>
<TLINK f_id="e6" s_id="e9" class="overlap" AnnConf="High"/>
<TLINK f_id="e14" s_id="e15" class="overlap" AnnConf="High"/>
<TLINK f_id="e17" s_id="e18" class="before" AnnConf="High"/>
<TLINK f_id="e20" s_id="e21" class="before" AnnConf="High"/>
<TLINK f_id="e21" s_id="e22" class="before" AnnConf="Low"/>
<TLINK f_id="e25" s_id="e26" class="before" AnnConf="High"/>
<TLINK f_id="e29" s_id="e30" class="before" AnnConf="High"/>
<TLINK f_id="e30" s_id="e31" class="before" AnnConf="High"/>
<TLINK f_id="e32" s_id="e33" class="before" AnnConf="High"/>
<TLINK f_id="e34" s_id="e35" class="before" AnnConf="High"/>
<TLINK f_id="e44" s_id="e45" class="before" AnnConf="High"/>
<TLINK f_id="e46" s_id="e47" class="before" AnnConf="High"/>
</document>