<document>
<token id="1"> मुलिया </token>
<token id="2"> हरी-हरी </token>
<token id="3"> घास </token>
<token id="4"> का </token>
<token id="5"> गट्ठा </token>
<token id="6"> लेकर </token>
<token id="7"> आयी </token>
<token id="8"> , </token>
<token id="9"> तो </token>
<token id="10"> उसका </token>
<token id="11"> गेहुआं </token>
<token id="12"> रंग </token>
<token id="13"> कुछ </token>
<token id="14"> तमतमाया </token>
<token id="15"> हुआ </token>
<token id="16"> था </token>
<token id="17"> और </token>
<token id="18"> बड़ी-बड़ी </token>
<token id="19"> मद-भरी </token>
<token id="20"> आंखो </token>
<token id="21"> में </token>
<token id="22"> शंका </token>
<token id="23"> समाई </token>
<token id="24"> हुई </token>
<token id="25"> थी </token>
<token id="26"> . </token>
<token id="27"> महावीर </token>
<token id="28"> ने </token>
<token id="29"> उसका </token>
<token id="30"> तमतमाया </token>
<token id="31"> हुआ </token>
<token id="32"> चेहरा </token>
<token id="33"> देखकर </token>
<token id="34"> पूछा- </token>
<token id="35"> क्या </token>
<token id="36"> है </token>
<token id="37"> मुलिया </token>
<token id="38"> , </token>
<token id="39"> आज </token>
<token id="40"> कैसा </token>
<token id="41"> जी </token>
<token id="42"> है </token>
<token id="43"> . </token>
<token id="44"> मुलिया </token>
<token id="45"> ने </token>
<token id="46"> कुछ </token>
<token id="47"> जवाब </token>
<token id="48"> न </token>
<token id="49"> दिया- </token>
<token id="50"> उसकी </token>
<token id="51"> आंखें </token>
<token id="52"> डबडबा </token>
<token id="53"> गयीं </token>
<token id="54"> ! </token>
<token id="55"> महावीर </token>
<token id="56"> ने </token>
<token id="57"> समीप </token>
<token id="58"> आकर </token>
<token id="59"> पूछा- </token>
<token id="60"> क्या </token>
<token id="61"> हुआ </token>
<token id="62"> है </token>
<token id="63"> , </token>
<token id="64"> बताती </token>
<token id="65"> क्यों </token>
<token id="66"> नहीं </token>
<token id="67"> ? </token>
<token id="68"> किसी </token>
<token id="69"> ने </token>
<token id="70"> कुछ </token>
<token id="71"> कहा </token>
<token id="72"> है </token>
<token id="73"> , </token>
<token id="74"> अम्मां </token>
<token id="75"> ने </token>
<token id="76"> डांटा </token>
<token id="77"> है </token>
<token id="78"> , </token>
<token id="79"> क्यों </token>
<token id="80"> इतनी </token>
<token id="81"> उदास </token>
<token id="82"> है </token>
<token id="83"> ? </token>
<token id="84"> मुलिया </token>
<token id="85"> ने </token>
<token id="86"> सिसककर </token>
<token id="87"> कहा- </token>
<token id="88"> कुछ </token>
<token id="89"> नहीं </token>
<token id="90"> , </token>
<token id="91"> हुआ </token>
<token id="92"> क्या </token>
<token id="93"> है </token>
<token id="94"> , </token>
<token id="95"> अच्छी </token>
<token id="96"> तो </token>
<token id="97"> हूं </token>
<token id="98"> ? </token>
<token id="99"> महावीर </token>
<token id="100"> ने </token>
<token id="101"> मुलिया </token>
<token id="102"> को </token>
<token id="103"> सिर </token>
<token id="104"> से </token>
<token id="105"> पांव </token>
<token id="106"> तक </token>
<token id="107"> देखकर </token>
<token id="108"> कहा- </token>
<token id="109"> चुपचाप </token>
<token id="110"> रोयेगी </token>
<token id="111"> , </token>
<token id="112"> बतायेगी </token>
<token id="113"> नहीं </token>
<token id="114"> ? </token>
<token id="115"> मुलिया </token>
<token id="116"> ने </token>
<token id="117"> बात </token>
<token id="118"> टालकर </token>
<token id="119"> कहा- </token>
<token id="120"> कोई </token>
<token id="121"> बात </token>
<token id="122"> भी </token>
<token id="123"> हो </token>
<token id="124"> , </token>
<token id="125"> क्या </token>
<token id="126"> बताऊं </token>
<token id="127"> . </token>
<token id="128"> मुलिया </token>
<token id="129"> इस </token>
<token id="130"> ऊसर </token>
<token id="131"> में </token>
<token id="132"> गुलाब </token>
<token id="133"> का </token>
<token id="134"> फूल </token>
<token id="135"> थी </token>
<token id="136"> . </token>
<token id="137"> गेहुआं </token>
<token id="138"> रंग </token>
<token id="139"> था </token>
<token id="140"> , </token>
<token id="141"> हिरन </token>
<token id="142"> की-सी </token>
<token id="143"> आंखें </token>
<token id="144"> , </token>
<token id="145"> नीचे </token>
<token id="146"> खिंचा </token>
<token id="147"> हुआ </token>
<token id="148"> चिबुक </token>
<token id="149"> , </token>
<token id="150"> कपोलों </token>
<token id="151"> पर </token>
<token id="152"> हलकी </token>
<token id="153"> लालिमा </token>
<token id="154"> , </token>
<token id="155"> बड़ी-बड़ी </token>
<token id="156"> नुकीली </token>
<token id="157"> पलकें </token>
<token id="158"> , </token>
<token id="159"> आंखो </token>
<token id="160"> में </token>
<token id="161"> एक </token>
<token id="162"> विचित्र </token>
<token id="163"> आर्द्रता </token>
<token id="164"> , </token>
<token id="165"> जिसमें </token>
<token id="166"> एक </token>
<token id="167"> स्पष्ट </token>
<token id="168"> वेदना </token>
<token id="169"> , </token>
<token id="170"> एक </token>
<token id="171"> मूक </token>
<token id="172"> व्यथा </token>
<token id="173"> झलकती </token>
<token id="174"> रहती </token>
<token id="175"> थी </token>
<token id="176"> . </token>
<EVENT id="e13" class="IAC" tokens="5,6" AnnConf="High"/>
<EVENT id="e14" class="OCC" tokens="7" AnnConf="High"/>
<EVENT id="e1" class="OCC" tokens="14,15,16" AnnConf="High"/>
<EVENT id="e2" class="OCC" tokens="23,24,25" AnnConf="High"/>
<EVENT id="e15" class="PER" tokens="33" AnnConf="High"/>
<EVENT id="e16" class="OCC" tokens="34" AnnConf="High"/>
<EVENT id="e17" class="OCC" tokens="47,48,49" AnnConf="High"/>
<EVENT id="e4" class="OCC" tokens="51,52,53" AnnConf="High"/>
<EVENT id="e5" class="IAC" tokens="57,58" AnnConf="High"/>
<EVENT id="e18" class="OCC" tokens="59" AnnConf="High"/>
<EVENT id="e6" class="REP" tokens="71,72" AnnConf="High"/>
<EVENT id="e7" class="OCC" tokens="76,77" AnnConf="High"/>
<EVENT id="e19" class="OCC" tokens="87" AnnConf="High"/>
<EVENT id="e8" class="PER" tokens="107" AnnConf="High"/>
<EVENT id="e20" class="OCC" tokens="108" AnnConf="High"/>
<EVENT id="e9" class="OCC" tokens="117,118" AnnConf="High"/>
<EVENT id="e21" class="OCC" tokens="119" AnnConf="High"/>
<EVENT id="e10" class="OCC" tokens="126" AnnConf="High"/>
<EVENT id="e12" class="OCC" tokens="173,174,175" AnnConf="High"/>
<STATE id="s5" class="DESC" tokens="30,31" AnnConf="High"/>
<STATE id="s1" class="DECL" tokens="42" AnnConf="High"/>
<STATE id="s2" class="DESC" tokens="61,62" AnnConf="High"/>
<STATE id="s3" class="DESC" tokens="93" AnnConf="High"/>
<STATE id="s4" class="DECL" tokens="135" AnnConf="High"/>
<STATE id="e22" class="DESC" tokens="146,147" AnnConf="High"/>
<SLINK f_id="e6" s_id="e7" AnnConf="Medium"/>
<SLINK f_id="e13" s_id="e14" AnnConf="High"/>
<SLINK f_id="e15" s_id="e16" AnnConf="High"/>
<SLINK f_id="e5" s_id="e18" AnnConf="High"/>
<SLINK f_id="e8" s_id="e20" AnnConf="High"/>
<TLINK f_id="e14" s_id="e1" class="before" AnnConf="Medium"/>
<TLINK f_id="e16" s_id="e17" class="before" AnnConf="High"/>
<TLINK f_id="e9" s_id="e21" class="before" AnnConf="Low"/>
</document>